{"word_index": {"the": 1, "of": 2, "to": 3, "was": 4, "at": 5, "is": 6, "her": 7, "sister": 8, "on": 9, "or": 10, "had": 11, "it": 12, "in": 13, "scepticism": 14, "as": 15, "knowledge": 16, "alice": 17, "beginning": 18, "get": 19, "very": 20, "tired": 21, "sitting": 22, "by": 23, "bank": 24, "once": 25, "twice": 26, "she": 27, "peeped": 28, "into": 29, "book": 30, "reading": 31, "but": 32, "no": 33, "pictures": 34, "conversations": 35, "buda": 36, "pesth": 37, "seems": 38, "a": 39, "wonderful": 40, "place": 41, "left": 42, "munich": 43, "8": 44, "35": 45, "p": 46, "m": 47, "1st": 48, "may": 49, "arriving": 50, "vienna": 51, "early": 52, "next": 53, "morning": 54, "much": 55, "result": 56, "be": 57, "content": 58, "with": 59, "what": 60, "we": 61, "present": 62, "know": 63, "for": 64, "most": 65, "part": 66, "shut": 67, "our": 68, "ears": 69, "against": 70, "conviction": 71, "theater": 72, "district": 73, "teeming": 74, "heart": 75, "midtown": 76, "west": 77, "pedestrian": 78, "plazas": 79, "times": 80, "square": 81, "costumed": 82, "characters": 83, "beckon": 84, "energetic": 85, "crowds": 86, "under": 87, "pulsing": 88, "lights": 89, "towering": 90, "digital": 91, "billboards": 92}, "max_len": 20, "vocabulary_size": 1000}